balert
