Metadata-Version: 1.1
Name: Balert
Version: 1.0.7
Summary: A speaking battery's charge level
Home-page: https://github.com/tushar-rishav/balert/
Author: Tushar Gautam
Author-email: tushar.rishav@gmail.com
License: GNU General Public License v3 (GPLv3)
Keywords: reminder,battery,notification,voice alert,python
Platform: UNKNOWN
Classifier: Operating System :: POSIX :: Linux
Classifier: Programming Language :: Python
Classifier: Programming Language :: Python :: 2.7
Classifier: Topic :: System :: Monitoring
